SimpleCovidAPI/__init__.py
SimpleCovidAPI/sca.py
SimpleCovidAPI-0.3.dist-info/LICENSE
SimpleCovidAPI-0.3.dist-info/METADATA
SimpleCovidAPI-0.3.dist-info/WHEEL
SimpleCovidAPI-0.3.dist-info/top_level.txt
SimpleCovidAPI-0.3.dist-info/RECORD
