Metadata-Version: 2.1
Name: SimpleCovidAPI
Version: 0.3
Summary: A client library for the SimpleCovidAPI to get covid19 data.
Home-page: https://github.com/gadhagod/SimpleCovidAPI
Author: GadhaGod
Author-email: gadhaguy13@gmail.com
License: UNKNOWN
Platform: UNKNOWN
Classifier: Programming Language :: Python :: 3
Classifier: License :: OSI Approved :: MIT License
Classifier: Operating System :: OS Independent
Requires-Python: >=3.6
Requires-Dist: requests
